[{"http://www.w3.org/1999/02/22-rdf-syntax-ns#type":"http://semweb.mmlab.be/ns/linkedconnections#Connection","arrivalStop":"http://irail.be/stations/NMBS/008896909","arrivalTime":"2017-07-19T20:48:00.000Z","departureStop":"http://irail.be/stations/NMBS/008896800","departureTime":"2017-07-19T20:43:00.000Z","http://vocab.gtfs.org/terms#route":"http://irail.be/routes/28","http://vocab.gtfs.org/terms#trip":"http://irail.be/trips/88____%3A007%3A%3A8891702%3A8896008%3A9%3A2304%3A20171208","@id":"http://belgium.linkedconnections.org/sncb/connections?departureTime=2017-07-19T20:40:00.000Z#1500496980000889680088____%3A007%3A%3A8891702%3A8896008%3A9%3A2304%3A20171208","gtfs:trip":"http://irail.be/trips/88____%3A007%3A%3A8891702%3A8896008%3A9%3A2304%3A20171208","previous":null},{"http://www.w3.org/1999/02/22-rdf-syntax-ns#type":"http://semweb.mmlab.be/ns/linkedconnections#Connection","arrivalStop":"http://irail.be/stations/NMBS/008896925","arrivalTime":"2017-07-19T21:16:00.000Z","departureStop":"http://irail.be/stations/NMBS/008896909","departureTime":"2017-07-19T21:11:00.000Z","http://vocab.gtfs.org/terms#route":"http://irail.be/routes/428","http://vocab.gtfs.org/terms#trip":"http://irail.be/trips/88____%3A007%3A%3A8891009%3A8896008%3A8%3A2325%3A20171208","@id":"http://belgium.linkedconnections.org/sncb/connections?departureTime=2017-07-19T21:10:00.000Z#1500498660000889690988____%3A007%3A%3A8891009%3A8896008%3A8%3A2325%3A20171208","gtfs:trip":"http://irail.be/trips/88____%3A007%3A%3A8891009%3A8896008%3A8%3A2325%3A20171208","previous":"http://belgium.linkedconnections.org/sncb/connections?departureTime=2017-07-19T20:40:00.000Z#1500496980000889680088____%3A007%3A%3A8891702%3A8896008%3A9%3A2304%3A20171208"},{"http://www.w3.org/1999/02/22-rdf-syntax-ns#type":"http://semweb.mmlab.be/ns/linkedconnections#Connection","arrivalStop":"http://irail.be/stations/NMBS/008896008","arrivalTime":"2017-07-19T21:25:00.000Z","departureStop":"http://irail.be/stations/NMBS/008896925","departureTime":"2017-07-19T21:16:00.000Z","http://vocab.gtfs.org/terms#route":"http://irail.be/routes/428","http://vocab.gtfs.org/terms#trip":"http://irail.be/trips/88____%3A007%3A%3A8891009%3A8896008%3A8%3A2325%3A20171208","@id":"http://belgium.linkedconnections.org/sncb/connections?departureTime=2017-07-19T21:10:00.000Z#1500498960000889692588____%3A007%3A%3A8891009%3A8896008%3A8%3A2325%3A20171208","gtfs:trip":"http://irail.be/trips/88____%3A007%3A%3A8891009%3A8896008%3A8%3A2325%3A20171208","previous":"http://belgium.linkedconnections.org/sncb/connections?departureTime=2017-07-19T21:10:00.000Z#1500498660000889690988____%3A007%3A%3A8891009%3A8896008%3A8%3A2325%3A20171208"},{"http://www.w3.org/1999/02/22-rdf-syntax-ns#type":"http://semweb.mmlab.be/ns/linkedconnections#Connection","arrivalStop":"http://irail.be/stations/NMBS/008896115","arrivalTime":"2017-07-20T02:21:00.000Z","departureStop":"http://irail.be/stations/NMBS/008896008","departureTime":"2017-07-20T02:16:00.000Z","http://vocab.gtfs.org/terms#route":"http://irail.be/routes/204","http://vocab.gtfs.org/terms#trip":"http://irail.be/trips/88____%3A007%3A%3A8896008%3A8811007%3A12%3A541%3A20171208","@id":"http://belgium.linkedconnections.org/sncb/connections?departureTime=2017-07-20T02:10:00.000Z#1500516960000889600888____%3A007%3A%3A8896008%3A8811007%3A12%3A541%3A20171208","gtfs:trip":"http://irail.be/trips/88____%3A007%3A%3A8896008%3A8811007%3A12%3A541%3A20171208","previous":"http://belgium.linkedconnections.org/sncb/connections?departureTime=2017-07-19T21:10:00.000Z#1500498960000889692588____%3A007%3A%3A8891009%3A8896008%3A8%3A2325%3A20171208"},{"http://www.w3.org/1999/02/22-rdf-syntax-ns#type":"http://semweb.mmlab.be/ns/linkedconnections#Connection","arrivalStop":"http://irail.be/stations/NMBS/008896149","arrivalTime":"2017-07-20T02:27:00.000Z","departureStop":"http://irail.be/stations/NMBS/008896115","departureTime":"2017-07-20T02:22:00.000Z","http://vocab.gtfs.org/terms#route":"http://irail.be/routes/204","http://vocab.gtfs.org/terms#trip":"http://irail.be/trips/88____%3A007%3A%3A8896008%3A8811007%3A12%3A541%3A20171208","@id":"http://belgium.linkedconnections.org/sncb/connections?departureTime=2017-07-20T02:20:00.000Z#1500517320000889611588____%3A007%3A%3A8896008%3A8811007%3A12%3A541%3A20171208","gtfs:trip":"http://irail.be/trips/88____%3A007%3A%3A8896008%3A8811007%3A12%3A541%3A20171208","previous":"http://belgium.linkedconnections.org/sncb/connections?departureTime=2017-07-20T02:10:00.000Z#1500516960000889600888____%3A007%3A%3A8896008%3A8811007%3A12%3A541%3A20171208"},{"http://www.w3.org/1999/02/22-rdf-syntax-ns#type":"http://semweb.mmlab.be/ns/linkedconnections#Connection","arrivalStop":"http://irail.be/stations/NMBS/008892106","arrivalTime":"2017-07-20T03:15:00.000Z","departureStop":"http://irail.be/stations/NMBS/008896149","departureTime":"2017-07-20T03:06:00.000Z","http://vocab.gtfs.org/terms#route":"http://irail.be/routes/310","http://vocab.gtfs.org/terms#trip":"http://irail.be/trips/88____%3A007%3A%3A8896735%3A8821006%3A27%3A623%3A20171208","@id":"http://belgium.linkedconnections.org/sncb/connections?departureTime=2017-07-20T03:00:00.000Z#1500519960000889614988____%3A007%3A%3A8896735%3A8821006%3A27%3A623%3A20171208","gtfs:trip":"http://irail.be/trips/88____%3A007%3A%3A8896735%3A8821006%3A27%3A623%3A20171208","previous":"http://belgium.linkedconnections.org/sncb/connections?departureTime=2017-07-20T02:20:00.000Z#1500517320000889611588____%3A007%3A%3A8896008%3A8811007%3A12%3A541%3A20171208"},{"http://www.w3.org/1999/02/22-rdf-syntax-ns#type":"http://semweb.mmlab.be/ns/linkedconnections#Connection","arrivalStop":"http://irail.be/stations/NMBS/008892080","arrivalTime":"2017-07-20T03:18:00.000Z","departureStop":"http://irail.be/stations/NMBS/008892106","departureTime":"2017-07-20T03:15:00.000Z","http://vocab.gtfs.org/terms#route":"http://irail.be/routes/310","http://vocab.gtfs.org/terms#trip":"http://irail.be/trips/88____%3A007%3A%3A8896735%3A8821006%3A27%3A623%3A20171208","@id":"http://belgium.linkedconnections.org/sncb/connections?departureTime=2017-07-20T03:10:00.000Z#1500520500000889210688____%3A007%3A%3A8896735%3A8821006%3A27%3A623%3A20171208","gtfs:trip":"http://irail.be/trips/88____%3A007%3A%3A8896735%3A8821006%3A27%3A623%3A20171208","previous":"http://belgium.linkedconnections.org/sncb/connections?departureTime=2017-07-20T03:00:00.000Z#1500519960000889614988____%3A007%3A%3A8896735%3A8821006%3A27%3A623%3A20171208"},{"http://www.w3.org/1999/02/22-rdf-syntax-ns#type":"http://semweb.mmlab.be/ns/linkedconnections#Connection","arrivalStop":"http://irail.be/stations/NMBS/008892007","arrivalTime":"2017-07-20T03:23:00.000Z","departureStop":"http://irail.be/stations/NMBS/008892080","departureTime":"2017-07-20T03:18:00.000Z","http://vocab.gtfs.org/terms#route":"http://irail.be/routes/310","http://vocab.gtfs.org/terms#trip":"http://irail.be/trips/88____%3A007%3A%3A8896735%3A8821006%3A27%3A623%3A20171208","@id":"http://belgium.linkedconnections.org/sncb/connections?departureTime=2017-07-20T03:10:00.000Z#1500520680000889208088____%3A007%3A%3A8896735%3A8821006%3A27%3A623%3A20171208","gtfs:trip":"http://irail.be/trips/88____%3A007%3A%3A8896735%3A8821006%3A27%3A623%3A20171208","previous":"http://belgium.linkedconnections.org/sncb/connections?departureTime=2017-07-20T03:10:00.000Z#1500520500000889210688____%3A007%3A%3A8896735%3A8821006%3A27%3A623%3A20171208"},{"http://www.w3.org/1999/02/22-rdf-syntax-ns#type":"http://semweb.mmlab.be/ns/linkedconnections#Connection","arrivalStop":"http://irail.be/stations/NMBS/008814001","arrivalTime":"2017-07-20T04:09:00.000Z","departureStop":"http://irail.be/stations/NMBS/008892007","departureTime":"2017-07-20T03:40:00.000Z","http://vocab.gtfs.org/terms#route":"http://irail.be/routes/42","http://vocab.gtfs.org/terms#trip":"http://irail.be/trips/88____%3A007%3A%3A8891009%3A8831765%3A36%3A754%3A20170901","@id":"http://belgium.linkedconnections.org/sncb/connections?departureTime=2017-07-20T03:40:00.000Z#1500522000000889200788____%3A007%3A%3A8891009%3A8831765%3A36%3A754%3A20170901","gtfs:trip":"http://irail.be/trips/88____%3A007%3A%3A8891009%3A8831765%3A36%3A754%3A20170901","previous":"http://belgium.linkedconnections.org/sncb/connections?departureTime=2017-07-20T03:10:00.000Z#1500520680000889208088____%3A007%3A%3A8896735%3A8821006%3A27%3A623%3A20171208"},{"http://www.w3.org/1999/02/22-rdf-syntax-ns#type":"http://semweb.mmlab.be/ns/linkedconnections#Connection","arrivalStop":"http://irail.be/stations/NMBS/008813037","arrivalTime":"2017-07-20T04:14:00.000Z","departureStop":"http://irail.be/stations/NMBS/008814001","departureTime":"2017-07-20T04:12:00.000Z","http://vocab.gtfs.org/terms#route":"http://irail.be/routes/42","http://vocab.gtfs.org/terms#trip":"http://irail.be/trips/88____%3A007%3A%3A8891009%3A8831765%3A36%3A754%3A20170901","@id":"http://belgium.linkedconnections.org/sncb/connections?departureTime=2017-07-20T04:10:00.000Z#1500523920000881400188____%3A007%3A%3A8891009%3A8831765%3A36%3A754%3A20170901","gtfs:trip":"http://irail.be/trips/88____%3A007%3A%3A8891009%3A8831765%3A36%3A754%3A20170901","previous":"http://belgium.linkedconnections.org/sncb/connections?departureTime=2017-07-20T03:40:00.000Z#1500522000000889200788____%3A007%3A%3A8891009%3A8831765%3A36%3A754%3A20170901"},{"http://www.w3.org/1999/02/22-rdf-syntax-ns#type":"http://semweb.mmlab.be/ns/linkedconnections#Connection","arrivalStop":"http://irail.be/stations/NMBS/008813003","arrivalTime":"2017-07-20T04:15:00.000Z","departureStop":"http://irail.be/stations/NMBS/008813037","departureTime":"2017-07-20T04:14:00.000Z","http://vocab.gtfs.org/terms#route":"http://irail.be/routes/42","http://vocab.gtfs.org/terms#trip":"http://irail.be/trips/88____%3A007%3A%3A8891009%3A8831765%3A36%3A754%3A20170901","@id":"http://belgium.linkedconnections.org/sncb/connections?departureTime=2017-07-20T04:10:00.000Z#1500524040000881303788____%3A007%3A%3A8891009%3A8831765%3A36%3A754%3A20170901","gtfs:trip":"http://irail.be/trips/88____%3A007%3A%3A8891009%3A8831765%3A36%3A754%3A20170901","previous":"http://belgium.linkedconnections.org/sncb/connections?departureTime=2017-07-20T04:10:00.000Z#1500523920000881400188____%3A007%3A%3A8891009%3A8831765%3A36%3A754%3A20170901"},{"http://www.w3.org/1999/02/22-rdf-syntax-ns#type":"http://semweb.mmlab.be/ns/linkedconnections#Connection","arrivalStop":"http://irail.be/stations/NMBS/008813045","arrivalTime":"2017-07-20T04:18:00.000Z","departureStop":"http://irail.be/stations/NMBS/008813003","departureTime":"2017-07-20T04:16:00.000Z","http://vocab.gtfs.org/terms#route":"http://irail.be/routes/42","http://vocab.gtfs.org/terms#trip":"http://irail.be/trips/88____%3A007%3A%3A8891009%3A8831765%3A36%3A754%3A20170901","@id":"http://belgium.linkedconnections.org/sncb/connections?departureTime=2017-07-20T04:10:00.000Z#1500524160000881300388____%3A007%3A%3A8891009%3A8831765%3A36%3A754%3A20170901","gtfs:trip":"http://irail.be/trips/88____%3A007%3A%3A8891009%3A8831765%3A36%3A754%3A20170901","previous":"http://belgium.linkedconnections.org/sncb/connections?departureTime=2017-07-20T04:10:00.000Z#1500524040000881303788____%3A007%3A%3A8891009%3A8831765%3A36%3A754%3A20170901"},{"http://www.w3.org/1999/02/22-rdf-syntax-ns#type":"http://semweb.mmlab.be/ns/linkedconnections#Connection","arrivalStop":"http://irail.be/stations/NMBS/008812005","arrivalTime":"2017-07-20T04:20:00.000Z","departureStop":"http://irail.be/stations/NMBS/008813045","departureTime":"2017-07-20T04:18:00.000Z","http://vocab.gtfs.org/terms#route":"http://irail.be/routes/42","http://vocab.gtfs.org/terms#trip":"http://irail.be/trips/88____%3A007%3A%3A8891009%3A8831765%3A36%3A754%3A20170901","@id":"http://belgium.linkedconnections.org/sncb/connections?departureTime=2017-07-20T04:10:00.000Z#1500524280000881304588____%3A007%3A%3A8891009%3A8831765%3A36%3A754%3A20170901","gtfs:trip":"http://irail.be/trips/88____%3A007%3A%3A8891009%3A8831765%3A36%3A754%3A20170901","previous":"http://belgium.linkedconnections.org/sncb/connections?departureTime=2017-07-20T04:10:00.000Z#1500524160000881300388____%3A007%3A%3A8891009%3A8831765%3A36%3A754%3A20170901"}]